{
  "project_info": {
    "project_number": "859279227888",
    "project_id": "misfinanzas-8926c",
    "storage_bucket": "misfinanzas-8926c.appspot.com"
  },
  "client": [
    {
      "client_info": {
        "mobilesdk_app_id": "1:859279227888:android:8fc66f9867ef37ada1fb35",
        "android_client_info": {
          "package_name": "com.juanmaotegui.misfinanzas"
        }
      },
      "oauth_client": [
        {
          "client_id": "859279227888-k27jc5lc1bffvsl8b143t501i184ghpi.apps.googleusercontent.com",
          "client_type": 3
        }
      ],
      "api_key": [
        {
          "current_key": "AIzaSyDrKkdjVlBSx5ypNQVOoXk5xzfg4kyzXJY"
        }
      ],
      "services": {
        "appinvite_service": {
          "other_platform_oauth_client": [
            {
              "client_id": "859279227888-k27jc5lc1bffvsl8b143t501i184ghpi.apps.googleusercontent.com",
              "client_type": 3
            }
          ]
        }
      }
    }
  ],
  "configuration_version": "1"
}